{
  "updatedAt": "2026-03-12T02:06:36Z",
  "items": [
    {
      "ts": "2026-03-12T02:06:36Z",
      "text": "Working: RUNNING: Scaffold production repo for dual-site platform"
    },
    {
      "ts": "2026-03-12T02:06:16Z",
      "text": "Working: RUNNING: Scaffold production repo for dual-site platform"
    },
    {
      "ts": "2026-03-12T02:05:57Z",
      "text": "Working: RUNNING: Scaffold production repo for dual-site platform"
    },
    {
      "ts": "2026-03-12T02:05:51Z",
      "text": "Working: RUNNING: Scaffold production repo for dual-site platform"
    },
    {
      "ts": "2026-03-12T02:05:50Z",
      "text": "Working: RUNNING: Scaffold production repo for dual-site platform"
    },
    {
      "ts": "2026-03-12T02:05:25Z",
      "text": "Working: RUNNING: Scaffold production repo for dual-site platform"
    },
    {
      "ts": "2026-03-12T02:05:03Z",
      "text": "Working: RUNNING: Scaffold production repo for dual-site platform"
    },
    {
      "ts": "2026-03-12T02:05:01Z",
      "text": "Working: RUNNING: Scaffold production repo for dual-site platform"
    },
    {
      "ts": "2026-03-12T02:05:00Z",
      "text": "Working: RUNNING: Scaffold production repo for dual-site platform"
    },
    {
      "ts": "2026-03-12T02:04:35Z",
      "text": "Working: RUNNING: Scaffold production repo for dual-site platform"
    },
    {
      "ts": "2026-03-12T02:04:17Z",
      "text": "Working: RUNNING: Scaffold production repo for dual-site platform"
    },
    {
      "ts": "2026-03-12T02:04:10Z",
      "text": "Working: RUNNING: Scaffold production repo for dual-site platform"
    },
    {
      "ts": "2026-03-12T02:04:00Z",
      "text": "Working: RUNNING: Scaffold production repo for dual-site platform"
    },
    {
      "ts": "2026-03-12T02:03:44Z",
      "text": "Working: RUNNING: Scaffold production repo for dual-site platform"
    },
    {
      "ts": "2026-03-12T02:03:31Z",
      "text": "Working: RUNNING: Scaffold production repo for dual-site platform"
    },
    {
      "ts": "2026-03-12T02:03:19Z",
      "text": "Working: RUNNING: Scaffold production repo for dual-site platform"
    },
    {
      "ts": "2026-03-12T02:03:03Z",
      "text": "Working: RUNNING: Scaffold production repo for dual-site platform"
    },
    {
      "ts": "2026-03-12T02:02:54Z",
      "text": "Working: RUNNING: Scaffold production repo for dual-site platform"
    },
    {
      "ts": "2026-03-12T02:02:45Z",
      "text": "Working: RUNNING: Scaffold production repo for dual-site platform"
    },
    {
      "ts": "2026-03-12T02:02:29Z",
      "text": "Working: RUNNING: Scaffold production repo for dual-site platform"
    },
    {
      "ts": "2026-03-12T02:02:04Z",
      "text": "Working: RUNNING: Scaffold production repo for dual-site platform"
    },
    {
      "ts": "2026-03-12T02:01:58Z",
      "text": "Working: RUNNING: Scaffold production repo for dual-site platform"
    },
    {
      "ts": "2026-03-12T02:01:57Z",
      "text": "Working: RUNNING: Scaffold production repo for dual-site platform"
    },
    {
      "ts": "2026-03-12T02:01:38Z",
      "text": "Working: RUNNING: Scaffold production repo for dual-site platform"
    },
    {
      "ts": "2026-03-12T02:01:13Z",
      "text": "Working: RUNNING: Scaffold production repo for dual-site platform"
    }
  ]
}
