{
  "updatedAt": "2026-03-30T12:02:24Z",
  "items": [
    {
      "ts": "2026-03-30T12:02:24Z",
      "text": "Working: RUNNING: Scaffold production repo for dual-site platform"
    },
    {
      "ts": "2026-03-30T12:02:06Z",
      "text": "Working: RUNNING: Scaffold production repo for dual-site platform"
    },
    {
      "ts": "2026-03-30T12:01:57Z",
      "text": "Working: RUNNING: Scaffold production repo for dual-site platform"
    },
    {
      "ts": "2026-03-30T12:01:41Z",
      "text": "Working: RUNNING: Scaffold production repo for dual-site platform"
    },
    {
      "ts": "2026-03-30T12:01:37Z",
      "text": "Working: RUNNING: Scaffold production repo for dual-site platform"
    },
    {
      "ts": "2026-03-30T12:01:16Z",
      "text": "Working: RUNNING: Scaffold production repo for dual-site platform"
    },
    {
      "ts": "2026-03-30T12:00:59Z",
      "text": "Working: RUNNING: Scaffold production repo for dual-site platform"
    },
    {
      "ts": "2026-03-30T12:00:51Z",
      "text": "Working: RUNNING: Scaffold production repo for dual-site platform"
    },
    {
      "ts": "2026-03-30T12:00:50Z",
      "text": "Working: RUNNING: Scaffold production repo for dual-site platform"
    },
    {
      "ts": "2026-03-30T12:00:25Z",
      "text": "Working: RUNNING: Scaffold production repo for dual-site platform"
    },
    {
      "ts": "2026-03-30T12:00:03Z",
      "text": "Working: RUNNING: Scaffold production repo for dual-site platform"
    },
    {
      "ts": "2026-03-30T12:00:00Z",
      "text": "Working: RUNNING: Scaffold production repo for dual-site platform"
    },
    {
      "ts": "2026-03-30T12:00:00Z",
      "text": "Working: RUNNING: Scaffold production repo for dual-site platform"
    },
    {
      "ts": "2026-03-30T11:59:35Z",
      "text": "Working: RUNNING: Scaffold production repo for dual-site platform"
    },
    {
      "ts": "2026-03-30T11:59:17Z",
      "text": "Working: RUNNING: Scaffold production repo for dual-site platform"
    },
    {
      "ts": "2026-03-30T11:59:10Z",
      "text": "Working: RUNNING: Scaffold production repo for dual-site platform"
    },
    {
      "ts": "2026-03-30T11:59:05Z",
      "text": "Working: RUNNING: Scaffold production repo for dual-site platform"
    },
    {
      "ts": "2026-03-30T11:58:44Z",
      "text": "Working: RUNNING: Scaffold production repo for dual-site platform"
    },
    {
      "ts": "2026-03-30T11:58:30Z",
      "text": "Working: RUNNING: Scaffold production repo for dual-site platform"
    },
    {
      "ts": "2026-03-30T11:58:19Z",
      "text": "Working: RUNNING: Scaffold production repo for dual-site platform"
    },
    {
      "ts": "2026-03-30T11:58:01Z",
      "text": "Working: RUNNING: Scaffold production repo for dual-site platform"
    },
    {
      "ts": "2026-03-30T11:57:54Z",
      "text": "Working: RUNNING: Scaffold production repo for dual-site platform"
    },
    {
      "ts": "2026-03-30T11:57:44Z",
      "text": "Working: RUNNING: Scaffold production repo for dual-site platform"
    },
    {
      "ts": "2026-03-30T11:57:29Z",
      "text": "Working: RUNNING: Scaffold production repo for dual-site platform"
    },
    {
      "ts": "2026-03-30T11:57:04Z",
      "text": "Working: RUNNING: Scaffold production repo for dual-site platform"
    }
  ]
}
