{
  "updatedAt": "2026-04-13T12:30:00Z",
  "items": [
    {
      "ts": "2026-04-13T12:30:00Z",
      "text": "Working: RUNNING: Scaffold production repo for dual-site platform"
    },
    {
      "ts": "2026-04-13T12:29:53Z",
      "text": "Working: RUNNING: Scaffold production repo for dual-site platform"
    },
    {
      "ts": "2026-04-13T12:29:52Z",
      "text": "Working: RUNNING: Scaffold production repo for dual-site platform"
    },
    {
      "ts": "2026-04-13T12:29:28Z",
      "text": "Working: RUNNING: Scaffold production repo for dual-site platform"
    },
    {
      "ts": "2026-04-13T12:29:06Z",
      "text": "Working: RUNNING: Scaffold production repo for dual-site platform"
    },
    {
      "ts": "2026-04-13T12:29:03Z",
      "text": "Working: RUNNING: Scaffold production repo for dual-site platform"
    },
    {
      "ts": "2026-04-13T12:28:58Z",
      "text": "Working: RUNNING: Scaffold production repo for dual-site platform"
    },
    {
      "ts": "2026-04-13T12:28:38Z",
      "text": "Working: RUNNING: Scaffold production repo for dual-site platform"
    },
    {
      "ts": "2026-04-13T12:28:19Z",
      "text": "Working: RUNNING: Scaffold production repo for dual-site platform"
    },
    {
      "ts": "2026-04-13T12:28:13Z",
      "text": "Working: RUNNING: Scaffold production repo for dual-site platform"
    },
    {
      "ts": "2026-04-13T12:27:59Z",
      "text": "Working: RUNNING: Scaffold production repo for dual-site platform"
    },
    {
      "ts": "2026-04-13T12:27:47Z",
      "text": "Working: RUNNING: Scaffold production repo for dual-site platform"
    },
    {
      "ts": "2026-04-13T12:27:33Z",
      "text": "Working: RUNNING: Scaffold production repo for dual-site platform"
    },
    {
      "ts": "2026-04-13T12:27:22Z",
      "text": "Working: RUNNING: Scaffold production repo for dual-site platform"
    },
    {
      "ts": "2026-04-13T12:27:03Z",
      "text": "Working: RUNNING: Scaffold production repo for dual-site platform"
    },
    {
      "ts": "2026-04-13T12:26:57Z",
      "text": "Working: RUNNING: Scaffold production repo for dual-site platform"
    },
    {
      "ts": "2026-04-13T12:26:47Z",
      "text": "Working: RUNNING: Scaffold production repo for dual-site platform"
    },
    {
      "ts": "2026-04-13T12:26:32Z",
      "text": "Working: RUNNING: Scaffold production repo for dual-site platform"
    },
    {
      "ts": "2026-04-13T12:26:07Z",
      "text": "Working: RUNNING: Scaffold production repo for dual-site platform"
    },
    {
      "ts": "2026-04-13T12:26:00Z",
      "text": "Working: RUNNING: Scaffold production repo for dual-site platform"
    },
    {
      "ts": "2026-04-13T12:26:00Z",
      "text": "Working: RUNNING: Scaffold production repo for dual-site platform"
    },
    {
      "ts": "2026-04-13T12:25:41Z",
      "text": "Working: RUNNING: Scaffold production repo for dual-site platform"
    },
    {
      "ts": "2026-04-13T12:25:16Z",
      "text": "Working: RUNNING: Scaffold production repo for dual-site platform"
    },
    {
      "ts": "2026-04-13T12:25:14Z",
      "text": "Working: RUNNING: Scaffold production repo for dual-site platform"
    },
    {
      "ts": "2026-04-13T12:25:01Z",
      "text": "Working: RUNNING: Scaffold production repo for dual-site platform"
    }
  ]
}
