{
  "updatedAt": "2026-02-23T22:39:59Z",
  "items": [
    {
      "ts": "2026-02-23T22:39:59Z",
      "text": "Working: RUNNING: Scaffold production repo for dual-site platform"
    },
    {
      "ts": "2026-02-23T22:39:59Z",
      "text": "Working: RUNNING: Scaffold production repo for dual-site platform"
    },
    {
      "ts": "2026-02-23T22:39:41Z",
      "text": "Working: RUNNING: Scaffold production repo for dual-site platform"
    },
    {
      "ts": "2026-02-23T22:39:23Z",
      "text": "Working: RUNNING: Scaffold production repo for dual-site platform"
    },
    {
      "ts": "2026-02-23T22:39:16Z",
      "text": "Working: RUNNING: Scaffold production repo for dual-site platform"
    },
    {
      "ts": "2026-02-23T22:39:13Z",
      "text": "Working: RUNNING: Scaffold production repo for dual-site platform"
    },
    {
      "ts": "2026-02-23T22:38:55Z",
      "text": "Working: RUNNING: Scaffold production repo for dual-site platform"
    },
    {
      "ts": "2026-02-23T22:38:51Z",
      "text": "Working: RUNNING: Scaffold production repo for dual-site platform"
    },
    {
      "ts": "2026-02-23T22:38:26Z",
      "text": "Working: RUNNING: Scaffold production repo for dual-site platform"
    },
    {
      "ts": "2026-02-23T22:38:25Z",
      "text": "Working: RUNNING: Scaffold production repo for dual-site platform"
    },
    {
      "ts": "2026-02-23T22:38:00Z",
      "text": "Working: RUNNING: Scaffold production repo for dual-site platform"
    },
    {
      "ts": "2026-02-23T22:37:59Z",
      "text": "Working: RUNNING: Scaffold production repo for dual-site platform"
    },
    {
      "ts": "2026-02-23T22:37:40Z",
      "text": "Working: RUNNING: Scaffold production repo for dual-site platform"
    },
    {
      "ts": "2026-02-23T22:37:35Z",
      "text": "Working: RUNNING: Scaffold production repo for dual-site platform"
    },
    {
      "ts": "2026-02-23T22:37:10Z",
      "text": "Working: RUNNING: Scaffold production repo for dual-site platform"
    },
    {
      "ts": "2026-02-23T22:37:00Z",
      "text": "Working: RUNNING: Scaffold production repo for dual-site platform"
    },
    {
      "ts": "2026-02-23T22:36:54Z",
      "text": "Working: RUNNING: Scaffold production repo for dual-site platform"
    },
    {
      "ts": "2026-02-23T22:36:45Z",
      "text": "Working: RUNNING: Scaffold production repo for dual-site platform"
    },
    {
      "ts": "2026-02-23T22:36:19Z",
      "text": "Working: RUNNING: Scaffold production repo for dual-site platform"
    },
    {
      "ts": "2026-02-23T22:36:08Z",
      "text": "Working: RUNNING: Scaffold production repo for dual-site platform"
    },
    {
      "ts": "2026-02-23T22:35:57Z",
      "text": "Working: RUNNING: Scaffold production repo for dual-site platform"
    },
    {
      "ts": "2026-02-23T22:35:54Z",
      "text": "Working: RUNNING: Scaffold production repo for dual-site platform"
    },
    {
      "ts": "2026-02-23T22:35:29Z",
      "text": "Working: RUNNING: Scaffold production repo for dual-site platform"
    },
    {
      "ts": "2026-02-23T22:35:21Z",
      "text": "Working: RUNNING: Scaffold production repo for dual-site platform"
    },
    {
      "ts": "2026-02-23T22:35:04Z",
      "text": "Working: RUNNING: Scaffold production repo for dual-site platform"
    }
  ]
}
