{
  "updatedAt": "2026-04-07T16:31:03Z",
  "items": [
    {
      "ts": "2026-04-07T16:31:03Z",
      "text": "Working: RUNNING: Scaffold production repo for dual-site platform"
    },
    {
      "ts": "2026-04-07T16:30:43Z",
      "text": "Working: RUNNING: Scaffold production repo for dual-site platform"
    },
    {
      "ts": "2026-04-07T16:30:18Z",
      "text": "Working: RUNNING: Scaffold production repo for dual-site platform"
    },
    {
      "ts": "2026-04-07T16:30:17Z",
      "text": "Working: RUNNING: Scaffold production repo for dual-site platform"
    },
    {
      "ts": "2026-04-07T16:30:00Z",
      "text": "Working: RUNNING: Scaffold production repo for dual-site platform"
    },
    {
      "ts": "2026-04-07T16:29:53Z",
      "text": "Working: RUNNING: Scaffold production repo for dual-site platform"
    },
    {
      "ts": "2026-04-07T16:29:30Z",
      "text": "Working: RUNNING: Scaffold production repo for dual-site platform"
    },
    {
      "ts": "2026-04-07T16:29:27Z",
      "text": "Working: RUNNING: Scaffold production repo for dual-site platform"
    },
    {
      "ts": "2026-04-07T16:29:05Z",
      "text": "Working: RUNNING: Scaffold production repo for dual-site platform"
    },
    {
      "ts": "2026-04-07T16:29:02Z",
      "text": "Working: RUNNING: Scaffold production repo for dual-site platform"
    },
    {
      "ts": "2026-04-07T16:28:44Z",
      "text": "Working: RUNNING: Scaffold production repo for dual-site platform"
    },
    {
      "ts": "2026-04-07T16:28:37Z",
      "text": "Working: RUNNING: Scaffold production repo for dual-site platform"
    },
    {
      "ts": "2026-04-07T16:28:12Z",
      "text": "Working: RUNNING: Scaffold production repo for dual-site platform"
    },
    {
      "ts": "2026-04-07T16:28:03Z",
      "text": "Working: RUNNING: Scaffold production repo for dual-site platform"
    },
    {
      "ts": "2026-04-07T16:27:58Z",
      "text": "Working: RUNNING: Scaffold production repo for dual-site platform"
    },
    {
      "ts": "2026-04-07T16:27:47Z",
      "text": "Working: RUNNING: Scaffold production repo for dual-site platform"
    },
    {
      "ts": "2026-04-07T16:27:21Z",
      "text": "Working: RUNNING: Scaffold production repo for dual-site platform"
    },
    {
      "ts": "2026-04-07T16:27:11Z",
      "text": "Working: RUNNING: Scaffold production repo for dual-site platform"
    },
    {
      "ts": "2026-04-07T16:27:02Z",
      "text": "Working: RUNNING: Scaffold production repo for dual-site platform"
    },
    {
      "ts": "2026-04-07T16:26:56Z",
      "text": "Working: RUNNING: Scaffold production repo for dual-site platform"
    },
    {
      "ts": "2026-04-07T16:26:31Z",
      "text": "Working: RUNNING: Scaffold production repo for dual-site platform"
    },
    {
      "ts": "2026-04-07T16:26:24Z",
      "text": "Working: RUNNING: Scaffold production repo for dual-site platform"
    },
    {
      "ts": "2026-04-07T16:26:06Z",
      "text": "Working: RUNNING: Scaffold production repo for dual-site platform"
    },
    {
      "ts": "2026-04-07T16:26:02Z",
      "text": "Working: RUNNING: Scaffold production repo for dual-site platform"
    },
    {
      "ts": "2026-04-07T16:25:40Z",
      "text": "Working: RUNNING: Scaffold production repo for dual-site platform"
    }
  ]
}
